odoo/addons/quality_control_issue/README.rst
odoo/addons/quality_control_issue/__init__.py
odoo/addons/quality_control_issue/__manifest__.py
odoo/addons/quality_control_issue/data/qc_issue_sequence.xml
odoo/addons/quality_control_issue/data/qc_stage_data.xml
odoo/addons/quality_control_issue/i18n/de.po
odoo/addons/quality_control_issue/i18n/quality_control_issue.pot
odoo/addons/quality_control_issue/models/__init__.py
odoo/addons/quality_control_issue/models/qc_issue.py
odoo/addons/quality_control_issue/models/qc_issue_stage.py
odoo/addons/quality_control_issue/models/qc_problem.py
odoo/addons/quality_control_issue/models/qc_problem_group.py
odoo/addons/quality_control_issue/models/qc_stage.py
odoo/addons/quality_control_issue/models/stock_scrap.py
odoo/addons/quality_control_issue/readme/CONFIGURE.rst
odoo/addons/quality_control_issue/readme/CONTRIBUTORS.rst
odoo/addons/quality_control_issue/readme/CREDITS.rst
odoo/addons/quality_control_issue/readme/DESCRIPTION.rst
odoo/addons/quality_control_issue/readme/ROADMAP.rst
odoo/addons/quality_control_issue/readme/USAGE.rst
odoo/addons/quality_control_issue/security/ir.model.access.csv
odoo/addons/quality_control_issue/security/quality_control_issue_security.xml
odoo/addons/quality_control_issue/static/description/icon.png
odoo/addons/quality_control_issue/static/description/icon.svg
odoo/addons/quality_control_issue/static/description/index.html
odoo/addons/quality_control_issue/tests/__init__.py
odoo/addons/quality_control_issue/tests/test_quality_control_issue.py
odoo/addons/quality_control_issue/views/qc_issue_stage.xml
odoo/addons/quality_control_issue/views/qc_issue_view.xml
odoo/addons/quality_control_issue/views/qc_problem_group_view.xml
odoo/addons/quality_control_issue/views/qc_problem_stage.xml
odoo/addons/quality_control_issue/views/qc_problem_view.xml
odoo/addons/quality_control_issue/views/qc_team_dashboard_view.xml
odoo11_addon_quality_control_issue-11.0.1.1.0.dist-info/METADATA
odoo11_addon_quality_control_issue-11.0.1.1.0.dist-info/RECORD
odoo11_addon_quality_control_issue-11.0.1.1.0.dist-info/WHEEL
odoo11_addon_quality_control_issue-11.0.1.1.0.dist-info/top_level.txt
