Metadata-Version: 2.1
Name: odoo11-addon-quality-control-issue
Version: 11.0.1.1.0
Summary: Allow to manage and report Quality Control Issues.
Home-page: https://odoo-community.org/
Author: Eficent , Odoo Community Association (OCA)
Author-email: support@odoo-community.org
License: AGPL-3
Platform: UNKNOWN
Classifier: Programming Language :: Python
Classifier: Framework :: Odoo
Classifier: License :: OSI Approved :: GNU Affero General Public License v3
Classifier: Development Status :: 5 - Production/Stable
Requires-Python: >=2.7, !=3.0.*, !=3.1.*, !=3.2.*, !=3.3.*, !=3.4.*
Requires-Dist: odoo11-addon-quality-control
Requires-Dist: odoo11-addon-quality-control-team
Requires-Dist: odoo (<11.1dev,>=11.0a)
